scau_jwxt_auth/__init__.py
scau_jwxt_auth/jwxt.py
scau_jwxt_auth-0.1.2.dist-info/licenses/LICENSE
scau_jwxt_auth-0.1.2.dist-info/METADATA
scau_jwxt_auth-0.1.2.dist-info/WHEEL
scau_jwxt_auth-0.1.2.dist-info/top_level.txt
scau_jwxt_auth-0.1.2.dist-info/RECORD
