Metadata-Version: 2.4
Name: scau_jwxt_auth
Version: 0.1.2
Summary: A package for authenticating with SCAU JWXT system.
Author-email: CBYellowstone <administrator@mail.ystone.top>
Project-URL: Homepage, https://github.com/CberYellowstone/SCAU_JWXT_Auth
Project-URL: Issues, https://github.com/CberYellowstone/SCAU_JWXT_Auth/issues
Classifier: Programming Language :: Python :: 3
Classifier: License :: OSI Approved :: GNU Affero General Public License v3 or later (AGPLv3+)
Classifier: Operating System :: OS Independent
Requires-Python: >=3.10
License-File: LICENSE
Requires-Dist: ddddocr>=1.5.6
Requires-Dist: requests>=2.32.3
Requires-Dist: Pillow>=11.2.0
Requires-Dist: playwright>=1.51.0
Dynamic: license-file
